odoo9_addon_stock_orderpoint_manual_procurement-9.0.1.0.0-py2.7-nspkg.pth
odoo_addons/stock_orderpoint_manual_procurement/__openerp__.py
odoo_addons/stock_orderpoint_manual_procurement/__init__.py
odoo_addons/stock_orderpoint_manual_procurement/README.rst
odoo_addons/stock_orderpoint_manual_procurement/security/stock_orderpoint_manual_procurement_security.xml
odoo_addons/stock_orderpoint_manual_procurement/models/__init__.py
odoo_addons/stock_orderpoint_manual_procurement/models/stock_warehouse_orderpoint.py
odoo_addons/stock_orderpoint_manual_procurement/views/stock_warehouse_orderpoint_view.xml
odoo_addons/stock_orderpoint_manual_procurement/views/procurement_order_view.xml
odoo_addons/stock_orderpoint_manual_procurement/wizards/make_procurement_orderpoint.py
odoo_addons/stock_orderpoint_manual_procurement/wizards/__init__.py
odoo_addons/stock_orderpoint_manual_procurement/wizards/make_procurement_orderpoint_view.xml
odoo_addons/stock_orderpoint_manual_procurement/tests/__init__.py
odoo_addons/stock_orderpoint_manual_procurement/tests/test_stock_orderpoint_manual_procurement.py
odoo_addons/stock_orderpoint_manual_procurement/static/description/icon.png
odoo9_addon_stock_orderpoint_manual_procurement-9.0.1.0.0.dist-info/top_level.txt
odoo9_addon_stock_orderpoint_manual_procurement-9.0.1.0.0.dist-info/WHEEL
odoo9_addon_stock_orderpoint_manual_procurement-9.0.1.0.0.dist-info/RECORD
odoo9_addon_stock_orderpoint_manual_procurement-9.0.1.0.0.dist-info/metadata.json
odoo9_addon_stock_orderpoint_manual_procurement-9.0.1.0.0.dist-info/DESCRIPTION.rst
odoo9_addon_stock_orderpoint_manual_procurement-9.0.1.0.0.dist-info/METADATA
odoo9_addon_stock_orderpoint_manual_procurement-9.0.1.0.0.dist-info/namespace_packages.txt
